crstlmeth/__init__.py
crstlmeth/cli/__init__.py
crstlmeth/cli/calculate/__init__.py
crstlmeth/cli/calculate/devi_calc_cmd.py
crstlmeth/cli/calculate/meth_calc_cmd.py
crstlmeth/cli/plot/__init__.py
crstlmeth/cli/plot/cn_plot_cmd.py
crstlmeth/cli/plot/meth_plot_cmd.py
crstlmeth/cli/reference/__init__.py
crstlmeth/cli/reference/create_reference_cmd.py
crstlmeth/cli/reference/view_reference_cmd.py
crstlmeth/config/__init__.py
crstlmeth/core/__init__.py
crstlmeth/core/cmeth.py
crstlmeth/core/copynumber.py
crstlmeth/core/discovery.py
crstlmeth/core/logging.py
crstlmeth/core/methylation.py
crstlmeth/core/parsers.py
crstlmeth/core/references.py
crstlmeth/core/regions.py
crstlmeth/core/stats.py
crstlmeth/kits/ME030_cn.bed
crstlmeth/kits/ME030_meth.bed
crstlmeth/kits/ME032_cn.bed
crstlmeth/kits/ME032_meth.bed
crstlmeth/kits/ME034_cn.bed
crstlmeth/kits/ME034_meth.bed
crstlmeth/kits/MLPA_all_cn.bed
crstlmeth/kits/MLPA_all_meth.bed
crstlmeth/refs/030.cmeth
crstlmeth/refs/032.cmeth
crstlmeth/refs/034.cmeth
crstlmeth/refs/all.cmeth
crstlmeth/viz/__init__.py
crstlmeth/viz/cn_plot.py
crstlmeth/viz/meth_plot.py
crstlmeth/viz/style.py
crstlmeth/web/__init__.py
crstlmeth/web/__main__.py
crstlmeth/web/app.py
crstlmeth/web/sidebar.py
crstlmeth/web/utils.py
crstlmeth/web/assets/logo.svg
crstlmeth/web/pages/00_home.py
crstlmeth/web/pages/01_analyze.py
crstlmeth/web/pages/02_references.py
crstlmeth/web/pages/03_calculate.py
crstlmeth/web/pages/04_kits.py
crstlmeth/web/pages/90_log.py
crstlmeth/web/pages/99_faq.py
crstlmeth-0.1.1.dist-info/licenses/LICENSE
crstlmeth-0.1.1.dist-info/METADATA
crstlmeth-0.1.1.dist-info/WHEEL
crstlmeth-0.1.1.dist-info/entry_points.txt
crstlmeth-0.1.1.dist-info/top_level.txt
crstlmeth-0.1.1.dist-info/RECORD
