Metadata-Version: 2.4
Name: crstlmeth
Version: 0.1.1
Summary: Visualize methylation and copy-number data from BedMethyl files
Author-email: Carlos Classen <cclassen@ukaachen.de>
License: MIT License
Requires-Python: >=3.12
License-File: LICENSE
Requires-Dist: click>=8.1
Requires-Dist: numpy>=2.0
Requires-Dist: pandas>=2.2
Requires-Dist: matplotlib>=3.8
Requires-Dist: seaborn>=0.13
Requires-Dist: scipy>=1.11
Requires-Dist: statsmodels>=0.14
Requires-Dist: pysam>=0.22
Requires-Dist: streamlit>=1.33
Provides-Extra: dev
Requires-Dist: black>=24.0; extra == "dev"
Requires-Dist: ruff>=0.4; extra == "dev"
Requires-Dist: pytest>=8.2; extra == "dev"
Requires-Dist: pre-commit>=3.7; extra == "dev"
Provides-Extra: docs
Requires-Dist: sphinx>=7.3; extra == "docs"
Requires-Dist: sphinx-click>=6.0; extra == "docs"
Requires-Dist: furo>=2024.8.6; extra == "docs"
Dynamic: license-file
